README.md
setup.py
pglite/__init__.py
pglite/__main__.py
pglite/pglite.py
pglite.egg-info/PKG-INFO
pglite.egg-info/SOURCES.txt
pglite.egg-info/dependency_links.txt
pglite.egg-info/not-zip-safe
pglite.egg-info/requires.txt
pglite.egg-info/top_level.txt
script/pglite
script/pglite.bat