Metadata-Version: 2.1
Name: pglite
Version: 1.0.12
Summary: PostgreSQLite
Home-page: UNKNOWN
Author: Oslandia
Author-email: infos@oslandia.com
Maintainer: Oslandia
Maintainer-email: infos@oslandia.com
License: LGPL
Keywords: postgresql,pglite
Platform: UNKNOWN
Classifier: Programming Language :: Python
Classifier: Topic :: Database :: Database Engines/Servers
Classifier: Topic :: Database :: Front-Ends
Classifier: Topic :: System :: Software Distribution
Classifier: Topic :: Software Development :: Libraries :: Python Modules
Provides-Extra: develop
